dgenome/__init__.py
dgenome/admin.py
dgenome/api.py
dgenome/apps.py
dgenome/models.py
dgenome/serializers.py
dgenome/urls.py
dgenome/views.py
dgenome/lib/__init__.py
dgenome/lib/utils.py
dgenome/tests/__init__.py
dgenome/tests/create_data.py
dgenome/tests/settings.py
dgenome/tests/test_models.py
dgenome/tests/test_response.py
dgenome/tests/urls.py
dgenome-1.1.8a3.data/scripts/load_genome_ucsc_refGenes.py
dgenome-1.1.8a3.dist-info/LICENSE
dgenome-1.1.8a3.dist-info/METADATA
dgenome-1.1.8a3.dist-info/WHEEL
dgenome-1.1.8a3.dist-info/top_level.txt
dgenome-1.1.8a3.dist-info/RECORD
